{
  "kind": "collectionType",
  "collectionName": "fee_structures",
  "info": {
    "singularName": "fee-structure",
    "pluralName": "fee-structures",
    "displayName": "Fee Structure",
    "description": ""
  },
  "options": {
    "draftAndPublish": true
  },
  "pluginOptions": {},
  "attributes": {
    "Name": {
      "type": "string",
      "required": true
    },
    "Description": {
      "type": "text",
      "required": true
    },
    "File": {
      "type": "media",
      "multiple": false,
      "required": true,
      "allowedTypes": [
        "images",
        "files"
      ]
    },
    "date": {
      "type": "date"
    }
  }
}
